raflash/RAConnect.py
raflash/RAFlasher.py
raflash/RAPacker.py
tests/test_parse.py
raflash-0.0.2.dist-info/LICENSE
raflash-0.0.2.dist-info/METADATA
raflash-0.0.2.dist-info/WHEEL
raflash-0.0.2.dist-info/entry_points.txt
raflash-0.0.2.dist-info/top_level.txt
raflash-0.0.2.dist-info/RECORD
