Metadata-Version: 2.1
Name: raflash
Version: 0.0.2
Summary: Flash tool for ROM bootloader for Renesas RA MCUs
Home-page: https://github.com/robinkrens/raflash
Author: Robin Krens
License: GNU
Keywords: Renesas RA flash bootloader
Classifier: Development Status :: 3 - Alpha
Classifier: Topic :: Software Development :: Embedded Systems
License-File: LICENSE
Requires-Dist: exceptiongroup >=1.2.0
Requires-Dist: future >=0.18.3
Requires-Dist: iniconfig >=2.0.0
Requires-Dist: iso8601 >=2.1.0
Requires-Dist: packaging >=23.2
Requires-Dist: pluggy >=1.4.0
Requires-Dist: pytest >=8.0.0
Requires-Dist: pyusb >=1.2.1
Requires-Dist: PyYAML >=6.0.1
Requires-Dist: tomli >=2.0.1
Requires-Dist: tqdm >=4.66.2
Requires-Dist: pyserial >=3.5
